flask_squirrel/__init__.py
flask_squirrel/__version__.py
flask_squirrel/startup/flask_app.py
flask_squirrel/startup/flask_main.py
flask_squirrel/table/db_placeholder_parser.py
flask_squirrel/table/dbtable.py
flask_squirrel/table/dbutil.py
flask_squirrel/table/linked_resource.py
flask_squirrel/table/viewspec.py
flask_squirrel/tools/mysql_to_sqlite_convert.py
flask_squirrel/util/dirmanager.py
flask_squirrel/util/fileutils.py
flask_squirrel/util/filter.py
flask_squirrel/util/session_auth.py
flask_squirrel/util/uploadroute.py
flask_squirrel/util/view_spec_generator.py
flask_squirrel-0.1.1.dist-info/LICENSE.rst
flask_squirrel-0.1.1.dist-info/METADATA
flask_squirrel-0.1.1.dist-info/WHEEL
flask_squirrel-0.1.1.dist-info/top_level.txt
flask_squirrel-0.1.1.dist-info/RECORD
