Metadata-Version: 2.1
Name: flask-squirrel
Version: 0.1.1
Summary: Database REST API provider based on Flask/Flask-RESTful
Home-page: https://github.com/ClNo/flask-squirrel
Author: Claudio Nold
Author-email: claudio.nold@gmx.net
License: MIT
Keywords: flask SQL REST datatables JSON
Platform: any
Classifier: Development Status :: 3 - Alpha
Classifier: Environment :: Web Environment
Classifier: Intended Audience :: Developers
Classifier: Framework :: Flask
Classifier: Programming Language :: Python :: 3
Classifier: Programming Language :: Python :: 3.6
Classifier: Programming Language :: Python :: 3.7
Classifier: Programming Language :: Python :: 3.8
Classifier: License :: OSI Approved :: MIT License
Classifier: Operating System :: OS Independent
Classifier: Topic :: Internet :: WWW/HTTP :: Dynamic Content
Classifier: Topic :: Software Development :: Libraries :: Python Modules
Requires-Python: >=3.6
Requires-Dist: Flask (>=1.1.0)
Requires-Dist: Flask-Cors (>=3.0.0)
Requires-Dist: Flask-HTTPAuth (>=3.3.0)
Requires-Dist: Flask-RESTful (>=0.3.7)
Requires-Dist: Flask-SQLAlchemy (>=2.4.0)
Requires-Dist: passlib
Provides-Extra: docs
Requires-Dist: sphinx ; extra == 'docs'
